api/__init__.py
fund/__init__.py
fund/getter.py
stock/__init__.py
stock/getter.py
thinkwide_finance-1.1.dist-info/METADATA
thinkwide_finance-1.1.dist-info/WHEEL
thinkwide_finance-1.1.dist-info/top_level.txt
thinkwide_finance-1.1.dist-info/RECORD
