Metadata-Version: 2.1
Name: thinkwide_finance
Version: 1.1
Summary: Thinkwide_Finance is an elegant and simple financial data interface library for Python, built for human beings! 
Author: ThinkWide
Classifier: Programming Language :: Python :: 3
Classifier: License :: OSI Approved :: MIT License
Classifier: Operating System :: OS Independent
Requires-Python: >=3.9
